odoo/addons/storage_image_product_import/README.rst
odoo/addons/storage_image_product_import/__init__.py
odoo/addons/storage_image_product_import/__manifest__.py
odoo/addons/storage_image_product_import/i18n/it.po
odoo/addons/storage_image_product_import/i18n/storage_image_product_import.pot
odoo/addons/storage_image_product_import/models/__init__.py
odoo/addons/storage_image_product_import/models/category_image_relation.py
odoo/addons/storage_image_product_import/models/product_image_relation.py
odoo/addons/storage_image_product_import/models/product_product.py
odoo/addons/storage_image_product_import/readme/CONTRIBUTORS.rst
odoo/addons/storage_image_product_import/readme/DESCRIPTION.rst
odoo/addons/storage_image_product_import/readme/USAGE.rst
odoo/addons/storage_image_product_import/static/description/icon.png
odoo/addons/storage_image_product_import/static/description/index.html
odoo14_addon_storage_image_product_import-14.0.1.0.1.dev7.dist-info/METADATA
odoo14_addon_storage_image_product_import-14.0.1.0.1.dev7.dist-info/WHEEL
odoo14_addon_storage_image_product_import-14.0.1.0.1.dev7.dist-info/top_level.txt
odoo14_addon_storage_image_product_import-14.0.1.0.1.dev7.dist-info/RECORD
