Metadata-Version: 2.1
Name: odoo14-addon-storage_image_product_import
Version: 14.0.1.0.1.dev7
Summary: Helper for importing image for csv base on url
Home-page: https://github.com/OCA/storage
Author: Akretion, Odoo Community Association (OCA)
Author-email: support@odoo-community.org
License: AGPL-3
Classifier: Programming Language :: Python
Classifier: Framework :: Odoo
Classifier: Framework :: Odoo :: 14.0
Classifier: License :: OSI Approved :: GNU Affero General Public License v3
Requires-Python: >=3.6
Requires-Dist: odoo14-addon-storage-image-import
Requires-Dist: odoo14-addon-storage-image-product
Requires-Dist: odoo<14.1dev,>=14.0a
